terrascript/__init__.py
terrascript/alicloud/__init__.py
terrascript/alicloud/d.py
terrascript/alicloud/r.py
terrascript/archive/__init__.py
terrascript/archive/d.py
terrascript/archive/r.py
terrascript/arukas/__init__.py
terrascript/arukas/d.py
terrascript/arukas/r.py
terrascript/aws/__init__.py
terrascript/aws/d.py
terrascript/aws/r.py
terrascript/azure/__init__.py
terrascript/azure/d.py
terrascript/azure/r.py
terrascript/azurerm/__init__.py
terrascript/azurerm/d.py
terrascript/azurerm/r.py
terrascript/bitbucket/__init__.py
terrascript/bitbucket/d.py
terrascript/bitbucket/r.py
terrascript/chef/__init__.py
terrascript/chef/d.py
terrascript/chef/r.py
terrascript/circonus/__init__.py
terrascript/circonus/d.py
terrascript/circonus/r.py
terrascript/clc/__init__.py
terrascript/clc/d.py
terrascript/clc/r.py
terrascript/cloudflare/__init__.py
terrascript/cloudflare/d.py
terrascript/cloudflare/r.py
terrascript/cloudscale/__init__.py
terrascript/cloudscale/d.py
terrascript/cloudscale/r.py
terrascript/cloudstack/__init__.py
terrascript/cloudstack/d.py
terrascript/cloudstack/r.py
terrascript/cobbler/__init__.py
terrascript/cobbler/d.py
terrascript/cobbler/r.py
terrascript/consul/__init__.py
terrascript/consul/d.py
terrascript/consul/r.py
terrascript/data/__init__.py
terrascript/data/alicloud.py
terrascript/data/archive.py
terrascript/data/arukas.py
terrascript/data/aws.py
terrascript/data/azure.py
terrascript/data/azurerm.py
terrascript/data/bitbucket.py
terrascript/data/chef.py
terrascript/data/circonus.py
terrascript/data/clc.py
terrascript/data/cloudflare.py
terrascript/data/cloudscale.py
terrascript/data/cloudstack.py
terrascript/data/cobbler.py
terrascript/data/datadog.py
terrascript/data/digitalocean.py
terrascript/data/dme.py
terrascript/data/dns.py
terrascript/data/dnsimple.py
terrascript/data/docker.py
terrascript/data/dyn.py
terrascript/data/external.py
terrascript/data/fastly.py
terrascript/data/github.py
terrascript/data/gitlab.py
terrascript/data/google.py
terrascript-0.9.0.dist-info/LICENSE
terrascript-0.9.0.dist-info/METADATA
terrascript-0.9.0.dist-info/WHEEL
terrascript-0.9.0.dist-info/top_level.txt
terrascript-0.9.0.dist-info/RECORD
