Metadata-Version: 2.1
Name: terrascript
Version: 0.9.0
Summary: Python module for creating Terraform configurations
Home-page: https://github.com/mjuenema/python-terrascript
Author: Markus Juenemann
Author-email: markus@juenemann.net
License: BSD 2-clause "Simplified" License
Keywords: terraform
Platform: UNKNOWN
Classifier: Development Status :: 4 - Beta
Classifier: Intended Audience :: Developers
Classifier: License :: OSI Approved :: BSD License
Classifier: Programming Language :: Python :: 3.6
Classifier: Programming Language :: Python :: 3.7
Classifier: Programming Language :: Python :: 3.8
